hello_world/__init__.py
hello_world/main.py
hello_world_prod_vk-0.0.1.dist-info/LICENSE
hello_world_prod_vk-0.0.1.dist-info/METADATA
hello_world_prod_vk-0.0.1.dist-info/WHEEL
hello_world_prod_vk-0.0.1.dist-info/top_level.txt
hello_world_prod_vk-0.0.1.dist-info/RECORD
