Metadata-Version: 2.1
Name: hello-world-prod-vk
Version: 0.0.1
Summary: A Hello World package
Home-page: https://github.com/vasilik23/sample-pypi-package
Author: Vasili Kamisarau
Author-email: vasili_kamisarau@epam.com
Classifier: Programming Language :: Python :: 3.11
Classifier: License :: OSI Approved :: MIT License
Classifier: Operating System :: OS Independent
Requires-Python: >=3.6
License-File: LICENSE
